dana/__init__.py
pmgdana-0.0.0.dist-info/LICENSE
pmgdana-0.0.0.dist-info/METADATA
pmgdana-0.0.0.dist-info/WHEEL
pmgdana-0.0.0.dist-info/top_level.txt
pmgdana-0.0.0.dist-info/RECORD
