Metadata-Version: 2.1
Name: pmgdana
Version: 0.0.0
Summary: PMG DANA Framework
Home-page: UNKNOWN
Author: Preston Meyer Group
Author-email: dev@pmgroup.ch
License: UNKNOWN
Platform: UNKNOWN
Classifier: Development Status :: 3 - Alpha
Classifier: Programming Language :: Python :: 3
Classifier: Operating System :: OS Independent
Classifier: Intended Audience :: Developers
Classifier: License :: OSI Approved :: MIT License
Requires-Python: ~=3.6
